{"is_source_file": true, "format": "Dart", "description": "Main entry point for a Flutter mobile application, defining the app structure with MaterialApp and a simple Scaffold with placeholder content.", "external_files": ["package:flutter/material.dart"], "external_methods": ["runApp", "MaterialApp", "ThemeData", "ColorScheme.fromSeed", "Colors.blue", "StatelessWidget", "StatefulWidget", "createState", "build", "Theme.of", "Scaffold", "AppBar", "Text", "Center", "Column", "SizedBox", "CircularProgressIndicator"], "published": ["main", "MyApp", "MyHomePage"], "classes": [{"name": "MyApp", "description": "Root widget of the application, setting up MaterialApp with themes and home page."}, {"name": "MyHomePage", "description": "Stateful widget representing the main screen with a title passed via constructor."}, {"name": "_MyHomePageState", "description": "State class managing the UI for MyHomePage, displaying a loading message."}], "methods": [{"name": "main", "description": "Entry point of the application, launching the MyApp widget."}, {"name": "build", "description": "Build method for MyApp returning MaterialApp."}, {"name": "build", "description": "Build method for _MyHomePageState constructing the UI layout."}, {"name": "createState", "description": "Creates the mutable state for MyHomePage."}], "calls": ["runApp", "MaterialApp", "ThemeData", "ColorScheme.fromSeed", "Theme.of", "Scaffold", "AppBar", "Text", "Center", "Column", "SizedBox", "CircularProgressIndicator"], "search-terms": ["Flutter", "main.dart", "MaterialApp", "Scaffold", "MyHomePage", "CircularProgressIndicator", "home screen"], "state": 2, "file_id": 3, "knowledge_revision": 37, "git_revision": "", "hash": "9979a5d60bf755982e7dcc18fb294549", "format-version": 4, "code-base-name": "mobile_frontend", "filename": "mobile_frontend/lib/main.dart", "revision_history": [{"37": ""}]}